ybl_mcp_server/__init__.py
ybl_mcp_server/constants.py
ybl_mcp_server/exceptions.py
ybl_mcp_server/models.py
ybl_mcp_server/registry.py
ybl_mcp_server/server.py
ybl_mcp_server/prompts/__init__.py
ybl_mcp_server/prompts/base.py
ybl_mcp_server/prompts/note_prompts.py
ybl_mcp_server/resources/__init__.py
ybl_mcp_server/resources/base.py
ybl_mcp_server/resources/notes.py
ybl_mcp_server/tools/__init__.py
ybl_mcp_server/tools/base.py
ybl_mcp_server/tools/note_tools.py
ybl_mcp_server/utils/__init__.py
ybl_mcp_server/utils/logging.py
ybl_mcp_server-0.1.1.dist-info/METADATA
ybl_mcp_server-0.1.1.dist-info/WHEEL
ybl_mcp_server-0.1.1.dist-info/entry_points.txt
ybl_mcp_server-0.1.1.dist-info/RECORD
