Metadata-Version: 2.4
Name: ybl-mcp-server
Version: 0.1.1
Summary: A MCP server project
Author-email: FAYBL <faybl@faybl.com>
Requires-Python: >=3.11.7
Requires-Dist: mcp>=1.6.0
Provides-Extra: dev
Requires-Dist: black>=25.1.0; extra == 'dev'
Requires-Dist: ruff>=0.11.2; extra == 'dev'
Requires-Dist: toml-sort>=0.24.2; extra == 'dev'
